nicegui_aggrid_enterprise/__init__.py
nicegui_aggrid_enterprise/aggrid.js
nicegui_aggrid_enterprise/aggrid.py
nicegui_aggrid_enterprise/py.typed
nicegui_aggrid_enterprise/version.py
nicegui_aggrid_enterprise/lib/aggrid/ag-grid-enterprise.js
nicegui_aggrid_enterprise/lib/aggrid/ag-grid-enterprise.min.js
nicegui_aggrid_enterprise-0.1.5.dist-info/METADATA
nicegui_aggrid_enterprise-0.1.5.dist-info/WHEEL
nicegui_aggrid_enterprise-0.1.5.dist-info/RECORD
