Metadata-Version: 2.4
Name: nicegui-aggrid-enterprise
Version: 0.1.5
Summary: Use Aggrid Enterprise in your NiceGUI app.
Author-email: Alex Pilon <alex.pilon@gmail.com>
License-Expression: MIT
Requires-Python: >=3.11
Requires-Dist: nicegui>=2.4.0
